{
	"configurations" : 
	[
		{
			"directories" : 
			[
				{
					"build" : ".",
					"jsonFile" : "directory-.-Debug-f5ebdc15457944623624.json",
					"minimumCMakeVersion" : 
					{
						"string" : "3.27"
					},
					"projectIndex" : 0,
					"source" : ".",
					"targetIndexes" : 
					[
						0
					]
				}
			],
			"name" : "Debug",
			"projects" : 
			[
				{
					"directoryIndexes" : 
					[
						0
					],
					"name" : "titanic",
					"targetIndexes" : 
					[
						0
					]
				}
			],
			"targets" : 
			[
				{
					"directoryIndex" : 0,
					"id" : "titanic::@6890427a1f51a3e7e1df",
					"jsonFile" : "target-titanic-Debug-00c9b4d2359dca190d86.json",
					"name" : "titanic",
					"projectIndex" : 0
				}
			]
		}
	],
	"kind" : "codemodel",
	"paths" : 
	{
		"build" : "/Users/mac/CLionProjects/titanic/cmake-build-debug",
		"source" : "/Users/mac/CLionProjects/titanic"
	},
	"version" : 
	{
		"major" : 2,
		"minor" : 6
	}
}
